gradio_hdrimage/__init__.py
gradio_hdrimage/hdrimage.py
gradio_hdrimage/hdrimage.pyi
gradio_hdrimage/templates/component/__vite-browser-external-2447137e.js
gradio_hdrimage/templates/component/index.js
gradio_hdrimage/templates/component/style.css
gradio_hdrimage/templates/component/wrapper-6f348d45-f837cf34.js
gradio_hdrimage/templates/example/index.js
gradio_hdrimage/templates/example/style.css
gradio_hdrimage-0.0.1.dist-info/METADATA
gradio_hdrimage-0.0.1.dist-info/WHEEL
gradio_hdrimage-0.0.1.dist-info/RECORD
